setup.py
matchengine/__init__.py
matchengine/engine.py
matchengine/schema.py
matchengine/settings.py
matchengine/utilities.py
matchengine/validation.py
matchengine.egg-info/PKG-INFO
matchengine.egg-info/SOURCES.txt
matchengine.egg-info/dependency_links.txt
matchengine.egg-info/requires.txt
matchengine.egg-info/top_level.txt