Metadata-Version: 1.0
Name: matchengine
Version: 0.1.1
Summary: clinical trial matching algorithm
Home-page: https://github.com/dfci/matchminer-engine
Author: Zachary Zwiesler
Author-email: zacharyt_zwiesler@dfci.harvard.edu
License: UNKNOWN
Platform: UNKNOWN
